<?xml version = '1.0' encoding = 'UTF-8'?>
<Diagram class="oracle.dbtools.crest.swingui.relational.DPVRelational" name="Relational_1" id="1AB97E76-DB7A-27FC-69B7-32E58DFB5462">
<createdBy>cosmi</createdBy>
<modifiedBy>cosmi</modifiedBy>
<createdTime>2021-05-03 09:05:21 UTC</createdTime>
<autoRoute>false</autoRoute>
<boxInbox>true</boxInbox>
<showLegend>false</showLegend>
<showLabels>false</showLabels>
<showRelAttributes>false</showRelAttributes>
<gridEnabled>false</gridEnabled>
<showGrid>false</showGrid>
<diagramColor>-1</diagramColor>
<display>false</display>
<notation>1</notation>
<objectViews>
<OView class="oracle.dbtools.crest.swingui.relational.TVTable" oid="1742A4FB-D356-5C1F-B3DF-0F106A54FDE9" otype="Table" vid="4F8D58C1-0C2A-D0AE-52BC-BE07AC07F0DC">
<hideElementsInCurrentOnly>false</hideElementsInCurrentOnly>
<bounds x="458" y="167" width="202" height="130"/>
</OView>
<OView class="oracle.dbtools.crest.swingui.relational.TVTable" oid="1C7CA986-E603-045F-BF25-F8D1339D93A9" otype="Table" vid="4FB14325-803C-1A18-D5FA-E1E079831AE0">
<hideElementsInCurrentOnly>false</hideElementsInCurrentOnly>
<bounds x="759" y="168" width="264" height="136"/>
</OView>
<OView class="oracle.dbtools.crest.swingui.relational.TVTable" oid="2229C77F-523E-8671-EE56-C1A011C4606E" otype="Table" vid="B9D6048B-1510-428A-6010-3F62364AEC69">
<hideElementsInCurrentOnly>false</hideElementsInCurrentOnly>
<bounds x="463" y="355" width="239" height="122"/>
</OView>
<OView class="oracle.dbtools.crest.swingui.relational.TVTable" oid="75F2FB8C-3581-2EC3-22AF-7311DECA9F3C" otype="Table" vid="8CE002CC-9833-CBE1-D085-77752720EA9F">
<hideElementsInCurrentOnly>false</hideElementsInCurrentOnly>
<bounds x="131" y="149" width="241" height="136"/>
</OView>
<OView class="oracle.dbtools.crest.swingui.relational.TVTable" oid="9981BD51-9E99-D56C-AC91-1419CCBF5A33" otype="Table" vid="46773FB9-7A1C-6537-5B62-29DEAA99543C">
<hideElementsInCurrentOnly>false</hideElementsInCurrentOnly>
<bounds x="750" y="376" width="335" height="108"/>
</OView>
<OView class="oracle.dbtools.crest.swingui.relational.TVTable" oid="DEB47843-1B39-69CA-4133-49DE61C57BC7" otype="Table" vid="5B61508A-ABAC-BDF2-74A0-2E9899940B2E">
<hideElementsInCurrentOnly>false</hideElementsInCurrentOnly>
<bounds x="64" y="332" width="325" height="192"/>
</OView>
<OView class="oracle.dbtools.crest.swingui.relational.TVTable" oid="EE832AB3-FC56-3F4D-B7D0-265D33E9612B" otype="Table" vid="E87AB846-9DF8-601F-2731-3545D89D9988">
<hideElementsInCurrentOnly>false</hideElementsInCurrentOnly>
<bounds x="457" y="24" width="253" height="108"/>
</OView>
</objectViews>
<connectors>
<Connector class="oracle.dbtools.crest.swingui.relational.TVFKRelation" oid="533980ED-F54F-8B56-9CB0-A69708919F09" otype="FKIndexAssociation" vid_source="4F8D58C1-0C2A-D0AE-52BC-BE07AC07F0DC" vid_target="B9D6048B-1510-428A-6010-3F62364AEC69">
<hideElementsInCurrentOnly>false</hideElementsInCurrentOnly>
<backgroundColor>-16777216</backgroundColor>
<lineWidth>1</lineWidth>
<points>
<point x="554" y="297"/>
<point x="554" y="355"/>
</points>
</Connector>
<Connector class="oracle.dbtools.crest.swingui.relational.TVFKRelation" oid="619291EF-94D0-508D-A8B0-82A1D570081B" otype="FKIndexAssociation" vid_source="4F8D58C1-0C2A-D0AE-52BC-BE07AC07F0DC" vid_target="4FB14325-803C-1A18-D5FA-E1E079831AE0">
<hideElementsInCurrentOnly>false</hideElementsInCurrentOnly>
<backgroundColor>-16777216</backgroundColor>
<lineWidth>1</lineWidth>
<points>
<point x="660" y="247"/>
<point x="759" y="247"/>
</points>
</Connector>
<Connector class="oracle.dbtools.crest.swingui.relational.TVFKRelation" oid="66B5FE9B-3A9B-1010-6881-D5D17DCC21C9" otype="FKIndexAssociation" vid_source="4F8D58C1-0C2A-D0AE-52BC-BE07AC07F0DC" vid_target="4FB14325-803C-1A18-D5FA-E1E079831AE0">
<hideElementsInCurrentOnly>false</hideElementsInCurrentOnly>
<backgroundColor>-16777216</backgroundColor>
<lineWidth>1</lineWidth>
<points>
<point x="660" y="232"/>
<point x="759" y="232"/>
</points>
</Connector>
<Connector class="oracle.dbtools.crest.swingui.relational.TVFKRelation" oid="A6412D70-0047-BE5C-AE38-A9A1C0F406BF" otype="FKIndexAssociation" vid_source="4F8D58C1-0C2A-D0AE-52BC-BE07AC07F0DC" vid_target="5B61508A-ABAC-BDF2-74A0-2E9899940B2E">
<hideElementsInCurrentOnly>false</hideElementsInCurrentOnly>
<backgroundColor>-16777216</backgroundColor>
<lineWidth>1</lineWidth>
<points>
<point x="458" y="291"/>
<point x="389" y="332"/>
</points>
</Connector>
<Connector class="oracle.dbtools.crest.swingui.relational.TVFKRelation" oid="AB2DE4B9-93B5-A324-76CC-DE9930887D87" otype="FKIndexAssociation" vid_source="4F8D58C1-0C2A-D0AE-52BC-BE07AC07F0DC" vid_target="B9D6048B-1510-428A-6010-3F62364AEC69">
<hideElementsInCurrentOnly>false</hideElementsInCurrentOnly>
<backgroundColor>-16777216</backgroundColor>
<lineWidth>1</lineWidth>
<points>
<point x="539" y="297"/>
<point x="539" y="355"/>
</points>
</Connector>
<Connector class="oracle.dbtools.crest.swingui.relational.TVFKRelation" oid="AD62DD5D-3ACA-BA6B-E407-124C1F307B9E" otype="FKIndexAssociation" vid_source="4F8D58C1-0C2A-D0AE-52BC-BE07AC07F0DC" vid_target="E87AB846-9DF8-601F-2731-3545D89D9988">
<hideElementsInCurrentOnly>false</hideElementsInCurrentOnly>
<backgroundColor>-16777216</backgroundColor>
<lineWidth>1</lineWidth>
<points>
<point x="531" y="167"/>
<point x="531" y="132"/>
</points>
</Connector>
<Connector class="oracle.dbtools.crest.swingui.relational.TVFKRelation" oid="CBA0411E-8085-BE89-4344-1235DF76807C" otype="FKIndexAssociation" vid_source="4FB14325-803C-1A18-D5FA-E1E079831AE0" vid_target="46773FB9-7A1C-6537-5B62-29DEAA99543C">
<hideElementsInCurrentOnly>false</hideElementsInCurrentOnly>
<backgroundColor>-16777216</backgroundColor>
<lineWidth>1</lineWidth>
<points>
<point x="891" y="304"/>
<point x="891" y="376"/>
</points>
</Connector>
<Connector class="oracle.dbtools.crest.swingui.relational.TVFKRelation" oid="CEDD1E85-AEF6-B847-F69A-F2A53A760F03" otype="FKIndexAssociation" vid_source="B9D6048B-1510-428A-6010-3F62364AEC69" vid_target="5B61508A-ABAC-BDF2-74A0-2E9899940B2E">
<hideElementsInCurrentOnly>false</hideElementsInCurrentOnly>
<backgroundColor>-16777216</backgroundColor>
<lineWidth>1</lineWidth>
<points>
<point x="463" y="431"/>
<point x="389" y="431"/>
</points>
</Connector>
<Connector class="oracle.dbtools.crest.swingui.relational.TVFKRelation" oid="EE561C23-8F13-B8A4-DBF4-0C7A00CD4088" otype="FKIndexAssociation" vid_source="4F8D58C1-0C2A-D0AE-52BC-BE07AC07F0DC" vid_target="8CE002CC-9833-CBE1-D085-77752720EA9F">
<hideElementsInCurrentOnly>false</hideElementsInCurrentOnly>
<backgroundColor>-16777216</backgroundColor>
<lineWidth>1</lineWidth>
<points>
<point x="458" y="226"/>
<point x="372" y="226"/>
</points>
</Connector>
</connectors>
</Diagram>
